buildgrid/__init__.py
buildgrid/_protos/__init__.py
buildgrid/_protos/build/__init__.py
buildgrid/_protos/build/bazel/__init__.py
buildgrid/_protos/build/bazel/remote/__init__.py
buildgrid/_protos/build/bazel/remote/asset/__init__.py
buildgrid/_protos/build/bazel/remote/asset/v1/__init__.py
buildgrid/_protos/build/bazel/remote/asset/v1/remote_asset_pb2.py
buildgrid/_protos/build/bazel/remote/asset/v1/remote_asset_pb2.pyi
buildgrid/_protos/build/bazel/remote/asset/v1/remote_asset_pb2_grpc.py
buildgrid/_protos/build/bazel/remote/asset/v1/remote_asset_pb2_grpc.pyi
buildgrid/_protos/build/bazel/remote/asset/v1/remote_asset_pb2_grpc_aio.py
buildgrid/_protos/build/bazel/remote/asset/v1/remote_asset_pb2_grpc_aio.pyi
buildgrid/_protos/build/bazel/remote/execution/__init__.py
buildgrid/_protos/build/bazel/remote/execution/v2/__init__.py
buildgrid/_protos/build/bazel/remote/execution/v2/remote_execution_pb2.py
buildgrid/_protos/build/bazel/remote/execution/v2/remote_execution_pb2.pyi
buildgrid/_protos/build/bazel/remote/execution/v2/remote_execution_pb2_grpc.py
buildgrid/_protos/build/bazel/remote/execution/v2/remote_execution_pb2_grpc.pyi
buildgrid/_protos/build/bazel/remote/execution/v2/remote_execution_pb2_grpc_aio.py
buildgrid/_protos/build/bazel/remote/execution/v2/remote_execution_pb2_grpc_aio.pyi
buildgrid/_protos/build/bazel/remote/logstream/__init__.py
buildgrid/_protos/build/bazel/remote/logstream/v1/__init__.py
buildgrid/_protos/build/bazel/remote/logstream/v1/remote_logstream_pb2.py
buildgrid/_protos/build/bazel/remote/logstream/v1/remote_logstream_pb2.pyi
buildgrid/_protos/build/bazel/remote/logstream/v1/remote_logstream_pb2_grpc.py
buildgrid/_protos/build/bazel/remote/logstream/v1/remote_logstream_pb2_grpc.pyi
buildgrid/_protos/build/bazel/remote/logstream/v1/remote_logstream_pb2_grpc_aio.py
buildgrid/_protos/build/bazel/remote/logstream/v1/remote_logstream_pb2_grpc_aio.pyi
buildgrid/_protos/build/bazel/semver/__init__.py
buildgrid-0.3.5.dist-info/licenses/LICENSE
buildgrid-0.3.5.dist-info/METADATA
buildgrid-0.3.5.dist-info/WHEEL
buildgrid-0.3.5.dist-info/entry_points.txt
buildgrid-0.3.5.dist-info/top_level.txt
buildgrid-0.3.5.dist-info/RECORD
