Metadata-Version: 2.4
Name: buildgrid
Version: 0.3.5
Summary: A remote execution service
License: Apache License, Version 2.0
Project-URL: Homepage, https://buildgrid.build
Project-URL: Documentation, https://buildgrid.build
Project-URL: Repository, https://gitlab.com/BuildGrid/buildgrid
Classifier: Programming Language :: Python :: 3
Requires-Python: >=3.11
License-File: LICENSE
Requires-Dist: boto3
Requires-Dist: botocore
Requires-Dist: dnspython
Requires-Dist: grpcio-reflection>=1.62.0
Requires-Dist: grpcio-health-checking>=1.62.0
Requires-Dist: grpcio>=1.62.0
Requires-Dist: importlib-resources
Requires-Dist: janus>=0.6.2
Requires-Dist: jinja2
Requires-Dist: protobuf
Requires-Dist: alembic
Requires-Dist: Click
Requires-Dist: SQLAlchemy>=2.0.44
Requires-Dist: pydantic>2.0
Requires-Dist: PyYAML>=6.0.1
Requires-Dist: jsonschema>=3.0.0
Requires-Dist: lark-parser
Requires-Dist: pycurl>=7.45.3
Requires-Dist: buildgrid-metering-client>=0.0.4
Requires-Dist: mmh3
Requires-Dist: cryptography
Requires-Dist: PyJWT
Requires-Dist: requests
Requires-Dist: sentry-sdk
Provides-Extra: database
Requires-Dist: psycopg2-binary; extra == "database"
Requires-Dist: psycopg>=3.2.10; extra == "database"
Provides-Extra: redis
Requires-Dist: fakeredis>=2.10.1; extra == "redis"
Requires-Dist: redis>=4.5.1; extra == "redis"
Requires-Dist: hiredis; extra == "redis"
Provides-Extra: docs
Requires-Dist: Sphinx<=8; extra == "docs"
Requires-Dist: sphinx-click; extra == "docs"
Requires-Dist: sphinx-rtd-theme; extra == "docs"
Requires-Dist: sphinxcontrib-apidoc; extra == "docs"
Provides-Extra: tests
Requires-Dist: coverage; extra == "tests"
Requires-Dist: cryptography>=38.0.0; extra == "tests"
Requires-Dist: flaky; extra == "tests"
Requires-Dist: flask; extra == "tests"
Requires-Dist: flask-cors; extra == "tests"
Requires-Dist: jwcrypto; extra == "tests"
Requires-Dist: moto<4.1.12; extra == "tests"
Requires-Dist: psutil; extra == "tests"
Requires-Dist: pycodestyle; extra == "tests"
Requires-Dist: pyopenssl>=22.0.0; extra == "tests"
Requires-Dist: pytest; extra == "tests"
Requires-Dist: pytest-cov; extra == "tests"
Requires-Dist: pytest-forked; extra == "tests"
Requires-Dist: pytest-pycodestyle; extra == "tests"
Requires-Dist: pytest-xdist; extra == "tests"
Requires-Dist: fakeredis>=2.10.1; extra == "tests"
Requires-Dist: redis>=4.5.1; extra == "tests"
Requires-Dist: pytest-postgresql>=7.0.2; extra == "tests"
Requires-Dist: psycopg2-binary; extra == "tests"
Requires-Dist: psycopg>=3.2.10; extra == "tests"
Provides-Extra: dev
Requires-Dist: pycodestyle; extra == "dev"
Requires-Dist: pytest; extra == "dev"
Requires-Dist: pytest-cov; extra == "dev"
Requires-Dist: pytest-forked; extra == "dev"
Requires-Dist: pytest-pycodestyle; extra == "dev"
Requires-Dist: pytest-xdist; extra == "dev"
Requires-Dist: memray; extra == "dev"
Requires-Dist: ruff; extra == "dev"
Requires-Dist: grpcio-tools; extra == "dev"
Requires-Dist: bump4version; extra == "dev"
Provides-Extra: mypy
Requires-Dist: mypy; extra == "mypy"
Requires-Dist: SQLAlchemy[mypy]; extra == "mypy"
Requires-Dist: grpc-stubs>=1.53; extra == "mypy"
Requires-Dist: mypy-protobuf<3.5; extra == "mypy"
Requires-Dist: boto3-stubs; extra == "mypy"
Requires-Dist: mypy-boto3-s3; extra == "mypy"
Requires-Dist: types-aiofiles; extra == "mypy"
Requires-Dist: types-cachetools; extra == "mypy"
Requires-Dist: types-docutils; extra == "mypy"
Requires-Dist: types-jsonschema; extra == "mypy"
Requires-Dist: types-protobuf; extra == "mypy"
Requires-Dist: types-psycopg2; extra == "mypy"
Requires-Dist: psycopg>=3.2.10; extra == "mypy"
Requires-Dist: types-pycurl>=7.45.3.20240421; extra == "mypy"
Requires-Dist: types-Pygments; extra == "mypy"
Requires-Dist: types-pyOpenSSL; extra == "mypy"
Requires-Dist: types-python-dateutil; extra == "mypy"
Requires-Dist: types-pyyaml; extra == "mypy"
Requires-Dist: types-redis; extra == "mypy"
Requires-Dist: types-requests; extra == "mypy"
Requires-Dist: types-setuptools; extra == "mypy"
Requires-Dist: types-urllib3; extra == "mypy"
Provides-Extra: all
Requires-Dist: buildgrid[database,dev,docs,mypy,redis,tests]; extra == "all"
Dynamic: license-file
